MANIFEST.in
README.txt
setup.py
XStatic_Leaflet_GestureHandling.egg-info/PKG-INFO
XStatic_Leaflet_GestureHandling.egg-info/SOURCES.txt
XStatic_Leaflet_GestureHandling.egg-info/dependency_links.txt
XStatic_Leaflet_GestureHandling.egg-info/namespace_packages.txt
XStatic_Leaflet_GestureHandling.egg-info/not-zip-safe
XStatic_Leaflet_GestureHandling.egg-info/requires.txt
XStatic_Leaflet_GestureHandling.egg-info/top_level.txt
xstatic/__init__.py
xstatic/pkg/__init__.py
xstatic/pkg/leaflet_gesturehandling/__init__.py
xstatic/pkg/leaflet_gesturehandling/data/leaflet-gesture-handling.css
xstatic/pkg/leaflet_gesturehandling/data/leaflet-gesture-handling.d.ts
xstatic/pkg/leaflet_gesturehandling/data/leaflet-gesture-handling.js
xstatic/pkg/leaflet_gesturehandling/data/leaflet-gesture-handling.min.css
xstatic/pkg/leaflet_gesturehandling/data/leaflet-gesture-handling.min.js
xstatic/pkg/leaflet_gesturehandling/data/leaflet-gesture-handling.min.js.map