Metadata-Version: 1.2
Name: XStatic-Leaflet-GestureHandling
Version: 1.1.8.1
Summary: Leaflet-GestureHandling 1.1.8 (XStatic packaging standard)
Home-page: https://github.com/elmarquis/Leaflet.GestureHandling
Maintainer: Frederic Peters
Maintainer-email: fpeters@entrouvert.com
License: (same as Leaflet-GestureHandling)
Keywords: leaflet_gesturehandling xstatic
Platform: any
